  2           0 LOAD_GLOBAL              0 (print)
              2 LOAD_CONST               1 ('AAAAAAAAAA')
              4 CALL_FUNCTION            1
              6 POP_TOP

  3           8 BUILD_LIST               0
             10 LOAD_CONST               2 ((127, 122, 98, 98, 128, 122, 74, 11, 6, 82, 3, 84, 3, 11, 4, 5, 88, 88, 2, 7, 84, 87, 82, 5, 82, 88, 12, 6, 12, 2, 88, 8, 84, 8, 87, 12, 5, 88, 87, 80))
             12 LIST_EXTEND              1
             14 STORE_FAST               0 (x)

 46          16 LOAD_FAST                0 (x)
             18 GET_ITER
        >>   20 FOR_ITER                28 (to 50)
             22 STORE_FAST               1 (i)

 47          24 LOAD_GLOBAL              0 (print)
             26 LOAD_GLOBAL              1 (chr)
             28 LOAD_FAST                1 (i)
             30 LOAD_CONST               3 (1)
             32 BINARY_SUBTRACT
             34 LOAD_CONST               4 (50)
             36 BINARY_XOR
             38 CALL_FUNCTION            1
             40 LOAD_CONST               5 ('')
             42 LOAD_CONST               6 (('end',))
             44 CALL_FUNCTION_KW         2
             46 POP_TOP
             48 JUMP_ABSOLUTE           20
        >>   50 LOAD_CONST               0 (None)
             52 RETURN_VALUE
